floating_point_multiplier.sv
// Floating Point Multiplier Implementation
// Format: 1 sign bit + 5 exponent bits + 6 fraction bits = 12 bits
// Exponent bias: +15

module floating_point_multiplier (
    input  wire         clk,
    input  wire         rst_n,
    input  wire [11:0]  a,      // First operand
    input  wire [11:0]  b,      // Second operand
    input  wire         valid_in,
    output reg  [11:0]  result,
    output reg          valid_out
);

    // Constants
    parameter BIAS = 15;
    parameter SATURATION_VALUE = 12'b011110110000; // exp=30, mantissa=110000
    parameter ZERO_VALUE = 12'b000000000000;

    // Internal wires and registers
    wire        sign_a, sign_b;
    wire [4:0]  exp_a, exp_b;
    wire [5:0]  frac_a, frac_b;
    wire [6:0]  norm_frac_a, norm_frac_b;
    wire [13:0] frac_mult_result;
    wire        zero_input;
    
    reg  [11:0] mult_result;
    reg  [5:0]  final_frac;
    reg  [4:0]  final_exp;
    reg  signed [7:0] result_exp_temp;
    reg         sign_result;
    reg         underflow, overflow;

    // Extract fields
    assign sign_a = a[11];
    assign exp_a  = a[10:6];
    assign frac_a = a[5:0];
    assign sign_b = b[11];
    assign exp_b  = b[10:6];
    assign frac_b = b[5:0];

    // Check for zero inputs
    assign zero_input = (a == 12'b0) || (b == 12'b0) || (exp_a == 5'b0) || (exp_b == 5'b0);

    // Add implicit leading 1 for normalized numbers
    assign norm_frac_a = {1'b1, frac_a};
    assign norm_frac_b = {1'b1, frac_b};

    // Multiply fractions
    assign frac_mult_result = norm_frac_a * norm_frac_b;

    // Combinational logic for multiplication
    always @(*) begin
        if (zero_input) begin
            mult_result = ZERO_VALUE;
        end else begin
            // Calculate result sign
            sign_result = sign_a ^ sign_b;
            
            // Calculate exponent using signed arithmetic - handle signed properly
            result_exp_temp = $signed({3'b000, exp_a}) + $signed({3'b000, exp_b}) - $signed({3'b000, 5'd15});
            
            // Handle normalization - check MSB of fraction product
            if (frac_mult_result[13] == 1'b1) begin
                // Product is >= 2.0, need to shift right and increment exponent
                final_frac = frac_mult_result[12:7];
                result_exp_temp = result_exp_temp + 1;
            end else begin
                // Product is < 2.0, take lower bits
                final_frac = frac_mult_result[11:6];
            end
            
            // Check for underflow (exponent <= 0)  
            underflow = (result_exp_temp <= 8'sd0);
            
            // Check for overflow (exponent >= 30)
            overflow = (result_exp_temp >= 8'sd30);
            
            if (underflow) begin
                mult_result = ZERO_VALUE;
            end else if (overflow) begin
                mult_result = SATURATION_VALUE;
            end else begin
                final_exp = result_exp_temp[4:0];
                mult_result = {sign_result, final_exp, final_frac};
            end
        end
    end

    // Sequential logic for pipeline
    always @(posedge clk or negedge rst_n) begin
        if (!rst_n) begin
            result <= 12'b0;
            valid_out <= 1'b0;
        end else begin
            valid_out <= valid_in;
            if (valid_in) begin
                result <= mult_result;
            end
        end
    end

endmodule

floating_point_multiplier_tb.sv
// Testbench for Floating Point Multiplier
// Tests the specific failing cases mentioned in the problem statement

`timescale 1ns/1ps

module floating_point_multiplier_tb;

    // Testbench signals
    logic        clk;
    logic        rst_n;
    logic [11:0] a, b;
    logic        valid_in;
    logic [11:0] result;
    logic        valid_out;
    
    // Test tracking
    int test_count = 0;
    int pass_count = 0;
    int fail_count = 0;
    
    // Instantiate DUT
    floating_point_multiplier dut (
        .clk(clk),
        .rst_n(rst_n),
        .a(a),
        .b(b),
        .valid_in(valid_in),
        .result(result),
        .valid_out(valid_out)
    );
    
    // Clock generation
    initial begin
        clk = 0;
        forever #5 clk = ~clk;
    end
    
    // Test procedure
    initial begin
        $dumpfile("floating_point_multiplier.vcd");
        $dumpvars(0, floating_point_multiplier_tb);
        
        // Initialize
        rst_n = 0;
        valid_in = 0;
        a = 0;
        b = 0;
        
        // Reset
        #20 rst_n = 1;
        #10;
        
        $display("\n=== Floating Point Multiplier Test Results ===");
        $display("Format: 1 sign + 5 exp + 6 frac = 12 bits, bias = 15");
        $display("Test format: Test# - Description: input_a * input_b = expected -> actual (PASS/FAIL)");
        
        // Test cases based on problem statement
        
        // Test 1: Basic multiplication (1.0 * 2.0 = 2.0)
        run_test("Test 1: Basic multiplication", 
                 12'b001111000000,  // exp=15(bias), frac=000000 = 1.0
                 12'b010000000000,  // exp=16(bias+1), frac=000000 = 2.0  
                 12'b010000000000); // exp=16(bias+1), frac=000000 = 2.0
        
        // Test 2: Zero multiplication
        run_test("Test 2: Zero multiplication",
                 12'b000000000000,  // 0.0
                 12'b001111100000,  // 1.0
                 12'b000000000000); // 0.0
        
        // Test 3: Sign test (positive * negative)
        run_test("Test 3: Sign test (pos * neg)",
                 12'b001111000000,  // +1.0
                 12'b101111000000,  // -1.0
                 12'b101111000000); // -1.0
        
        // Test 4: Sign test (negative * negative)  
        run_test("Test 4: Sign test (neg * neg)",
                 12'b101111000000,  // -1.0
                 12'b101111000000,  // -1.0
                 12'b001111000000); // +1.0
        
        // Test 5: Small * Small (underflow test) - This was failing
        run_test("Test 5: Small * Small (underflow test)",
                 12'b000010100000,  // exp=2(-13), small number
                 12'b000010100000,  // exp=2(-13), small number  
                 12'b000000000000); // Should underflow to 0, not saturate
        
        // Test 6: Large * Large (overflow test)
        run_test("Test 6: Large * Large (overflow test)",
                 12'b011101110000,  // exp=29(+14), large number
                 12'b011101110000,  // exp=29(+14), large number
                 12'b011110110000); // Should saturate
        
        // Test 7: Max exp * 1.0 - This was failing  
        run_test("Test 7: Max exp * 1.0",
                 12'b011101000000,  // exp=29(+14), max valid exp  
                 12'b001111000000,  // exp=15(bias), frac=000000 = 1.0
                 12'b011101000000); // Should preserve max exp, not saturate
        
        // Test 8: 1.0 * Max exp (commutative check)
        run_test("Test 8: 1.0 * Max exp (commutative check)",
                 12'b001111000000,  // 1.0
                 12'b011101000000,  // max valid exp
                 12'b011101000000); // Should preserve max exp
        
        // Test 9: Fractional multiplication (1.25 * 1.25 = 1.5625)
        run_test("Test 9: Fractional multiplication",
                 12'b001111010000,  // exp=15, frac=010000 = 1.25
                 12'b001111010000,  // exp=15, frac=010000 = 1.25
                 12'b001111100100); // Should be approximately 1.5625
        
        // Test 10: Edge case - minimum normalized * 1.0
        run_test("Test 10: Min normalized * 1.0",
                 12'b000001000000,  // exp=1(-14), minimum normalized
                 12'b001111000000,  // 1.0
                 12'b000001000000); // Should preserve minimum normalized
        
        // Test 11: Denormalized input (exp=0) should be treated as zero
        run_test("Test 11: Denormalized input",
                 12'b000000100000,  // exp=0, denormalized
                 12'b001111000000,  // 1.0
                 12'b000000000000); // Should be zero
        
        // Print final results
        $display("\n=== Test Summary ===");
        $display("Total tests: %0d", test_count);
        $display("Passed: %0d", pass_count);
        $display("Failed: %0d", fail_count);
        
        if (fail_count == 0) begin
            $display("*** ALL TESTS PASSED! ***");
        end else begin
            $display("*** %0d TESTS FAILED ***", fail_count);
        end
        
        $finish;
    end
    
    // Test execution task
    task run_test(string test_name, logic [11:0] input_a, logic [11:0] input_b, logic [11:0] expected);
        test_count++;
        
        // Apply inputs
        a = input_a;
        b = input_b;
        valid_in = 1;
        
        // Wait for result - simplified approach with proper timing
        @(posedge clk);
        valid_in = 0;
        #1; // Small delay to let values settle
        
        // Check result
        if (result == expected) begin
            $display("%s: %b * %b = %b -> %b (PASS)", 
                     test_name, input_a, input_b, expected, result);
            pass_count++;
        end else begin
            $display("%s: %b * %b = %b -> %b (FAIL)", 
                     test_name, input_a, input_b, expected, result);
            fail_count++;
            
            // Additional debug info for failed tests
            $display("  Expected: sign=%b, exp=%b(%0d), frac=%b", 
                     expected[11], expected[10:6], expected[10:6], expected[5:0]);
            $display("  Actual:   sign=%b, exp=%b(%0d), frac=%b", 
                     result[11], result[10:6], result[10:6], result[5:0]);
        end
        
        #10; // Small delay between tests
    endtask
    
endmodule

floating_point_multiplier.vcd
$date
	Sat Sep 20 01:21:57 2025
$end
$version
	Icarus Verilog
$end
$timescale
	1ps
$end
$scope module floating_point_multiplier_tb $end
$var wire 1 ! valid_out $end
$var wire 12 " result [11:0] $end
$var reg 12 # a [11:0] $end
$var reg 12 $ b [11:0] $end
$var reg 1 % clk $end
$var reg 1 & rst_n $end
$var reg 1 ' valid_in $end
$var integer 32 ( fail_count [31:0] $end
$var integer 32 ) pass_count [31:0] $end
$var integer 32 * test_count [31:0] $end
$scope module dut $end
$var wire 12 + a [11:0] $end
$var wire 12 , b [11:0] $end
$var wire 1 % clk $end
$var wire 1 & rst_n $end
$var wire 1 ' valid_in $end
$var wire 1 - zero_input $end
$var wire 1 . sign_b $end
$var wire 1 / sign_a $end
$var wire 7 0 norm_frac_b [6:0] $end
$var wire 7 1 norm_frac_a [6:0] $end
$var wire 14 2 frac_mult_result [13:0] $end
$var wire 6 3 frac_b [5:0] $end
$var wire 6 4 frac_a [5:0] $end
$var wire 5 5 exp_b [4:0] $end
$var wire 5 6 exp_a [4:0] $end
$var parameter 32 7 BIAS $end
$var parameter 12 8 SATURATION_VALUE $end
$var parameter 12 9 ZERO_VALUE $end
$var reg 5 : final_exp [4:0] $end
$var reg 6 ; final_frac [5:0] $end
$var reg 12 < mult_result [11:0] $end
$var reg 1 = overflow $end
$var reg 12 > result [11:0] $end
$var reg 8 ? result_exp_temp [7:0] $end
$var reg 1 @ sign_result $end
$var reg 1 A underflow $end
$var reg 1 ! valid_out $end
$upscope $end
$scope task run_test $end
$var reg 12 B expected [11:0] $end
$var reg 12 C input_a [11:0] $end
$var reg 12 D input_b [11:0] $end
$upscope $end
$upscope $end
$enddefinitions $end
$comment Show the parameter values. $end
$dumpall
b0 9
b11110110000 8
b1111 7
$end
#0
$dumpvars
bx D
bx C
bx B
xA
x@
bx ?
b0 >
x=
b0 <
bx ;
bx :
b0 6
b0 5
b0 4
b0 3
b1000000000000 2
b1000000 1
b1000000 0
0/
0.
1-
b0 ,
b0 +
b0 *
b0 )
b0 (
0'
0&
0%
b0 $
b0 #
b0 "
0!
$end
#5000
1%
#10000
0%
#15000
1%
#20000
0%
1&
#25000
1%
#30000
b10000000000 <
b10000 :
0=
0A
b0 ;
b10000 ?
0@
0-
b10000 5
b1111 6
0%
1'
b10000000000 $
b10000000000 ,
b1111000000 #
b1111000000 +
b1 *
b10000000000 B
b10000000000 D
b1111000000 C
#35000
0'
1%
#36000
b1 (
#40000
0%
#45000
1%
#46000
1-
b0 <
1A
b100000 ;
b0 ?
b1111 5
b1100000000000 2
b1100000 0
b100000 3
b0 6
1'
b1111100000 $
b1111100000 ,
b0 #
b0 +
b10 *
b0 B
b1111100000 D
b0 C
#50000
0%
#55000
0'
1%
#56000
b1 )
#60000
0%
#65000
1%
#66000
b101111000000 <
b1111 :
0A
b0 ;
b1111 ?
1@
0-
1.
b1000000000000 2
b1000000 0
b0 3
b1111 6
1'
b101111000000 $
b101111000000 ,
b1111000000 #
b1111000000 +
b11 *
b101111000000 B
b101111000000 D
b1111000000 C
#70000
0%
#75000
0'
1%
#76000
b10 (
#80000
0%
#85000
1%
#86000
b1111000000 <
0@
1/
1'
b101111000000 #
b101111000000 +
b100 *
b1111000000 B
b101111000000 C
#90000
0%
#95000
0'
1%
#96000
b11 (
#100000
0%
#105000
1%
#106000
b0 <
1A
b1000 ;
b11110110 ?
0.
b10 5
b1100000 0
b100000 3
0/
b10 6
b10010000000000 2
b1100000 1
b100000 4
1'
b10100000 $
b10100000 ,
b10100000 #
b10100000 +
b101 *
b0 B
b10100000 D
b10100000 C
#110000
0%
#115000
0'
1%
#116000
b10 )
#120000
0%
#125000
1%
#126000
b11110110000 <
1=
0A
b100010 ;
b101100 ?
b11101 5
b1110000 0
b110000 3
b11101 6
b11000100000000 2
b1110000 1
b110000 4
1'
b11101110000 $
b11101110000 ,
b11101110000 #
b11101110000 +
b110 *
b11110110000 B
b11101110000 D
b11101110000 C
#130000
0%
#135000
0'
1%
#136000
b100 (
#140000
0%
#145000
1%
#146000
b11101000000 <
b11101 :
0=
b0 ;
b11101 ?
b1111 5
b1000000 0
b0 3
b1000000000000 2
b1000000 1
b0 4
1'
b1111000000 $
b1111000000 ,
b11101000000 #
b11101000000 +
b111 *
b11101000000 B
b1111000000 D
b11101000000 C
#150000
0%
#155000
0'
1%
#156000
b101 (
#160000
0%
#165000
1%
#166000
b11101 5
b1111 6
1'
b11101000000 $
b11101000000 ,
b1111000000 #
b1111000000 +
b1000 *
b11101000000 D
b1111000000 C
#170000
0%
#175000
0'
1%
#176000
b110 (
#180000
0%
#185000
1%
#186000
b1111100100 <
b1111 :
b100100 ;
b1111 ?
b1111 5
b1010000 0
b10000 3
b1100100000000 2
b1010000 1
b10000 4
1'
b1111010000 $
b1111010000 ,
b1111010000 #
b1111010000 +
b1001 *
b1111100100 B
b1111010000 D
b1111010000 C
#190000
0%
#195000
0'
1%
#196000
b111 (
#200000
0%
#205000
1%
#206000
b1000000 <
b1 :
b0 ;
b1 ?
b1000000 0
b0 3
b1 6
b1000000000000 2
b1000000 1
b0 4
1'
b1111000000 $
b1111000000 ,
b1000000 #
b1000000 +
b1010 *
b1000000 B
b1111000000 D
b1000000 C
#210000
0%
#215000
0'
1%
#216000
b1000 (
#220000
0%
#225000
1%
#226000
1-
b0 <
1A
b100000 ;
b0 ?
b0 6
b1100000000000 2
b1100000 1
b100000 4
1'
b100000 #
b100000 +
b1011 *
b0 B
b100000 C
#230000
0%
#235000
0'
1%
#236000
b11 )
